example_pkg_umihico/__init__.py
example_pkg_umihico/__version__.py
example_pkg_umihico/funcs.py
example_pkg_umihico-0.2.8.dist-info/METADATA
example_pkg_umihico-0.2.8.dist-info/WHEEL
example_pkg_umihico-0.2.8.dist-info/top_level.txt
example_pkg_umihico-0.2.8.dist-info/RECORD
